README.md
setup.py
efficient_drive.egg-info/PKG-INFO
efficient_drive.egg-info/SOURCES.txt
efficient_drive.egg-info/dependency_links.txt
efficient_drive.egg-info/not-zip-safe
efficient_drive.egg-info/top_level.txt
torchsparse/__init__.py
torchsparse/point_tensor.py
torchsparse/sparse_tensor.py
torchsparse/nn/__init__.py
torchsparse/nn/functional/__init__.py
torchsparse/nn/functional/activation.py
torchsparse/nn/functional/conv.py
torchsparse/nn/functional/convert_neighbor_map.py
torchsparse/nn/functional/count.py
torchsparse/nn/functional/crop.py
torchsparse/nn/functional/devox.py
torchsparse/nn/functional/downsample.py
torchsparse/nn/functional/hash.py
torchsparse/nn/functional/pooling.py
torchsparse/nn/functional/query.py
torchsparse/nn/functional/voxelize.py
torchsparse/nn/modules/__init__.py
torchsparse/nn/modules/activation.py
torchsparse/nn/modules/conv.py
torchsparse/nn/modules/crop.py
torchsparse/nn/modules/norm.py
torchsparse/nn/modules/pooling.py
torchsparse/src/torchsparse_bindings_gpu.cpp
torchsparse/src/convolution/convolution.cpp
torchsparse/src/convolution/convolution_cpu.cpp
torchsparse/src/convolution/convolution_gpu.cu
torchsparse/src/hash/hash.cpp
torchsparse/src/hash/hash_cpu.cpp
torchsparse/src/hash/hash_gpu.cu
torchsparse/src/hashmap/hashmap.cu
torchsparse/src/hashmap/hashmap_cpu.cpp
torchsparse/src/interpolation/devox.cpp
torchsparse/src/interpolation/devox_cpu.cpp
torchsparse/src/interpolation/devox_deterministic.cpp
torchsparse/src/interpolation/devox_deterministic_gpu.cu
torchsparse/src/interpolation/devox_gpu.cu
torchsparse/src/others/convert_neighbor_map.cpp
torchsparse/src/others/convert_neighbor_map_cpu.cpp
torchsparse/src/others/convert_neighbor_map_gpu.cu
torchsparse/src/others/count.cpp
torchsparse/src/others/count_cpu.cpp
torchsparse/src/others/count_gpu.cu
torchsparse/src/others/insertion.cpp
torchsparse/src/others/insertion_cpu.cpp
torchsparse/src/others/insertion_gpu.cu
torchsparse/src/others/query.cpp
torchsparse/src/others/query_cpu.cpp
torchsparse/utils/__init__.py
torchsparse/utils/helpers.py
torchsparse/utils/kernel_region.py