Metadata-Version: 2.1
Name: efficient-drive
Version: 1.1.0
Summary: Efficient library for autonomous driving (under development).
Home-page: UNKNOWN
License: UNKNOWN
Platform: UNKNOWN
